textmine/__init__.py
textmine/api.py
textmine/cli.py
textmine/client.py
textmine/config.py
textmine/ui.py
textmine_cli-0.1.16.dist-info/licenses/LICENSE
textmine_cli-0.1.16.dist-info/METADATA
textmine_cli-0.1.16.dist-info/WHEEL
textmine_cli-0.1.16.dist-info/entry_points.txt
textmine_cli-0.1.16.dist-info/top_level.txt
textmine_cli-0.1.16.dist-info/RECORD
