Metadata-Version: 2.4
Name: textmine-cli
Version: 0.1.16
Summary: Retro terminal client for textmine.net - 1980s-style chat network
Author-email: "textmine.net" <contact@textmine.net>
License: MIT
Project-URL: Homepage, https://textmine.net
Project-URL: Repository, https://github.com/textmine/textmine-cli
Keywords: chat,terminal,retro,cli,messaging
Classifier: Development Status :: 4 - Beta
Classifier: Environment :: Console
Classifier: Intended Audience :: End Users/Desktop
Classifier: License :: OSI Approved :: MIT License
Classifier: Programming Language :: Python :: 3
Classifier: Programming Language :: Python :: 3.8
Classifier: Programming Language :: Python :: 3.9
Classifier: Programming Language :: Python :: 3.10
Classifier: Programming Language :: Python :: 3.11
Classifier: Topic :: Communications :: Chat
Requires-Python: >=3.8
License-File: LICENSE
Requires-Dist: rich>=13.0.0
Requires-Dist: click>=8.0.0
Requires-Dist: requests>=2.28.0
Requires-Dist: websockets>=11.0.0
Requires-Dist: keyring>=24.0.0
Dynamic: license-file
